text_vectorizer/__init__.py
text_vectorizer/version.txt
text_vectorizer-0.0.1.dist-info/METADATA
text_vectorizer-0.0.1.dist-info/WHEEL
text_vectorizer-0.0.1.dist-info/top_level.txt
text_vectorizer-0.0.1.dist-info/RECORD
